docite/__init__.py
docite/__main__.py
docite/cli.py
docite/convert.py
docite/py.typed
docite/utils.py
docite/assets/__init__.py
docite/assets/apa.csl
docite/assets/example_bibfile.bib
docite/assets/example_inputfile.md
docite/assets/example_outputfile.md
docite/assets/ieee.csl
docite-0.1.3.dist-info/LICENSE.txt
docite-0.1.3.dist-info/METADATA
docite-0.1.3.dist-info/WHEEL
docite-0.1.3.dist-info/entry_points.txt
docite-0.1.3.dist-info/top_level.txt
docite-0.1.3.dist-info/RECORD
